meaningcloud/ClassRequest.py
meaningcloud/ClassResponse.py
meaningcloud/ClusteringRequest.py
meaningcloud/ClusteringResponse.py
meaningcloud/DeepCategorizationRequest.py
meaningcloud/DeepCategorizationResponse.py
meaningcloud/LanguageRequest.py
meaningcloud/LanguageResponse.py
meaningcloud/ParserRequest.py
meaningcloud/ParserResponse.py
meaningcloud/Request.py
meaningcloud/Response.py
meaningcloud/SentimentRequest.py
meaningcloud/SentimentResponse.py
meaningcloud/SummarizationRequest.py
meaningcloud/SummarizationResponse.py
meaningcloud/TopicsRequest.py
meaningcloud/TopicsResponse.py
meaningcloud/__init__.py
MeaningCloud_python-1.2.3.dist-info/LICENSE
MeaningCloud_python-1.2.3.dist-info/METADATA
MeaningCloud_python-1.2.3.dist-info/WHEEL
MeaningCloud_python-1.2.3.dist-info/top_level.txt
MeaningCloud_python-1.2.3.dist-info/RECORD
