Metadata-Version: 2.1
Name: MeaningCloud-python
Version: 1.2.3
Summary: Official Python SDK for MeaningCloud APIs
Home-page: https://github.com/MeaningCloud/meaningcloud-python
Author: MeaningCloud
Author-email: support@meaningcloud.com
License: UNKNOWN
Keywords: nlp,MeaningCloud,text analytics
Platform: UNKNOWN
Classifier: Development Status :: 5 - Production/Stable
Classifier: Programming Language :: Python :: 2
Classifier: Programming Language :: Python :: 3
Classifier: Intended Audience :: Developers
Classifier: Intended Audience :: Information Technology
Classifier: Intended Audience :: Science/Research
Classifier: Topic :: Text Processing
Classifier: Topic :: Text Processing :: General
Classifier: Topic :: Text Processing :: Linguistic
Classifier: Topic :: Scientific/Engineering
Classifier: Topic :: Scientific/Engineering :: Artificial Intelligence
Classifier: Topic :: Scientific/Engineering :: Information Analysis
Provides-Extra: dev
Provides-Extra: test
